setup.py
scribe_monitor.egg-info/PKG-INFO
scribe_monitor.egg-info/SOURCES.txt
scribe_monitor.egg-info/dependency_links.txt
scribe_monitor.egg-info/not-zip-safe
scribe_monitor.egg-info/requires.txt
scribe_monitor.egg-info/top_level.txt
scribemonitor/__init__.py
scribemonitor/monitor.py
scribemonitor/scribe_monitor
scribemonitor/statsd_helper.py
scribemonitor/monitors/__init__.py
scribemonitor/monitors/file_store.py
scribemonitor/monitors/hdfs_store.py
scribemonitor/monitors/status.py