Metadata-Version: 1.0
Name: scribe-monitor
Version: 0.2
Summary: Monitor scribe server to statsd
Home-page: https://github.com/Zemanta/scribemonitor
Author: Jure Ham
Author-email: jure.ham@zemanta.com
License: Apache 2.0
Platform: any
